py_radix_sr-1.0.2.dist-info/licenses/LICENSE
radix/__init__.py
radix/_radix.cpython-314-darwin.so
radix/radix.py
py_radix_sr-1.0.2.dist-info/METADATA
py_radix_sr-1.0.2.dist-info/WHEEL
py_radix_sr-1.0.2.dist-info/top_level.txt
py_radix_sr-1.0.2.dist-info/RECORD
