Metadata-Version: 2.4
Name: py-radix-sr
Version: 1.0.2
Summary: Radix tree implementation
Home-page: https://github.com/SEKOIA-IO/py-radix
Maintainer: Sasha Romijn / Raphael Cohen
Maintainer-email: github@mxsasha.eu
License: BSD
Keywords: radix tree trie python routing networking
Classifier: Intended Audience :: Developers
Classifier: Topic :: Software Development :: Libraries :: Python Modules
Classifier: Topic :: System :: Networking
Classifier: License :: OSI Approved :: BSD License
Classifier: Programming Language :: Python :: 2
Classifier: Programming Language :: Python :: 2.7
Classifier: Programming Language :: Python :: 3
Classifier: Programming Language :: Python :: 3.3
Classifier: Programming Language :: Python :: 3.4
Classifier: Programming Language :: Python :: 3.5
License-File: LICENSE
Dynamic: classifier
Dynamic: description
Dynamic: home-page
Dynamic: keywords
Dynamic: license
Dynamic: license-file
Dynamic: maintainer
Dynamic: maintainer-email
Dynamic: summary
